simplescalcula/__init__.py
simplescalcula/calcula.py
simplescalcula-0.0.1.dist-info/LICENSE
simplescalcula-0.0.1.dist-info/METADATA
simplescalcula-0.0.1.dist-info/WHEEL
simplescalcula-0.0.1.dist-info/top_level.txt
simplescalcula-0.0.1.dist-info/RECORD
