Metadata-Version: 2.1
Name: simplescalcula
Version: 0.0.1
Summary: Meu primeiro pacote
Author: Luis Eduardo
Author-email: le1307114@gmail.com
Keywords: python pacote example
Classifier: Development Status :: 3 - Alpha
Classifier: Intended Audience :: Developers
Classifier: License :: OSI Approved :: MIT License
Classifier: Programming Language :: Python :: 3
Classifier: Operating System :: OS Independent
License-File: LICENSE
